ai_audio_detector/__init__.py
ai_audio_detector/__main__.py
ai_audio_detector-1.1.0.dist-info/licenses/LICENSE
tests/__init__.py
tests/benchmark.py
tests/conftest.py
tests/test_detector.py
tests/test_feature_extractor.py
tests/test_integration.py
ai_audio_detector-1.1.0.dist-info/METADATA
ai_audio_detector-1.1.0.dist-info/WHEEL
ai_audio_detector-1.1.0.dist-info/entry_points.txt
ai_audio_detector-1.1.0.dist-info/top_level.txt
ai_audio_detector-1.1.0.dist-info/RECORD
