Metadata-Version: 2.4
Name: ai-audio-detector
Version: 1.1.0
Summary: Machine learning system for detecting AI-generated audio using Benford's Law and advanced spectral features
Home-page: https://github.com/ajprice16/AI_Audio_Detection
Author: Alex Price
Author-email: ajprice@mail.wlu.edu
Project-URL: Bug Reports, https://github.com/ajprice16/AI_Audio_Detection/issues
Project-URL: Source, https://github.com/ajprice16/AI_Audio_Detection
Project-URL: Documentation, https://github.com/ajprice16/AI_Audio_Detection#readme
Keywords: ai detection audio machine-learning benford-law audio-analysis
Classifier: Development Status :: 4 - Beta
Classifier: Intended Audience :: Developers
Classifier: Intended Audience :: Science/Research
Classifier: Operating System :: OS Independent
Classifier: Programming Language :: Python :: 3
Classifier: Programming Language :: Python :: 3.8
Classifier: Programming Language :: Python :: 3.9
Classifier: Programming Language :: Python :: 3.10
Classifier: Programming Language :: Python :: 3.11
Classifier: Programming Language :: Python :: 3.12
Classifier: Programming Language :: Python :: 3.13
Classifier: Topic :: Scientific/Engineering :: Artificial Intelligence
Classifier: Topic :: Multimedia :: Sound/Audio :: Analysis
Requires-Python: >=3.8
License-File: LICENSE
Requires-Dist: numpy>=1.21.0
Requires-Dist: pandas>=1.3.0
Requires-Dist: librosa>=0.9.0
Requires-Dist: scikit-learn>=1.0.0
Requires-Dist: scipy>=1.7.0
Requires-Dist: matplotlib>=3.4.0
Requires-Dist: tqdm>=4.62.0
Requires-Dist: joblib>=1.1.0
Requires-Dist: pyyaml>=6.0
Requires-Dist: pathlib
Dynamic: author
Dynamic: author-email
Dynamic: classifier
Dynamic: description
Dynamic: description-content-type
Dynamic: home-page
Dynamic: keywords
Dynamic: license-file
Dynamic: project-url
Dynamic: requires-dist
Dynamic: requires-python
Dynamic: summary
